decorum
