Metadata-Version: 1.1
Name: Decorum
Version: 1.0.2
Summary: Tool for writing simple decorators.
Home-page: https://pypi.python.org/pypi/Decorum
Author: Zach Kelling
Author-email: zk@monoid.io
License: MIT
Keywords: decorator decorators
Platform: UNKNOWN
Classifier: Development Status :: 5 - Production/Stable
Classifier: Programming Language :: Python :: 2.7
Classifier: Programming Language :: Python :: 3.3
Classifier: Programming Language :: Python :: 3.4
Classifier: License :: OSI Approved :: MIT License
Classifier: Intended Audience :: Developers
